<?xml version="1.0" encoding="UTF-8" standalone="yes"?>








<item>
<title>[COLOR red]J[/COLOR][COLOR blue]H[/COLOR][COLOR red]G[/COLOR] THE PUNISHER (1989) </title>
<urlsolve>http://streamcloud.eu/j56dezlc2er2</urlsolve>
<thumbnail>https://static.comicvine.com/uploads/square_small/0/6063/870065-punisher_dolph_lundgren.jpg</thumbnail>
<fanart>https://static.comicvine.com/uploads/square_small/0/6063/870065-punisher_dolph_lundgren.jpg</fanart>
</item>




<item>
<title>[COLOR red]J[/COLOR][COLOR blue]H[/COLOR][COLOR red]G[/COLOR] The Punisher (2004) </title>
<urlsolve>http://streamcloud.eu/ex1zlp8fsxmb/El.castigador.avi.html</urlsolve>
<thumbnail>http://3.bp.blogspot.com/-9naVnbxXcZw/VdNZGa8tkVI/AAAAAAAAJxo/MMqOJ4snKJY/s1600/p13.jpg</thumbnail>
<fanart>http://3.bp.blogspot.com/-9naVnbxXcZw/VdNZGa8tkVI/AAAAAAAAJxo/MMqOJ4snKJY/s1600/p13.jpg</fanart>
</item>


<item>
<title>[COLOR red]J[/COLOR][COLOR blue]H[/COLOR][COLOR red]G[/COLOR] THE PUNISHER 2 (2008)</title>
<urlsolve>http://streamcloud.eu/h9qlw79y9oa4</urlsolve>
<thumbnail>https://pics.filmaffinity.com/punisher_war_zone-230941957-large.jpg</thumbnail>
<fanart>https://pics.filmaffinity.com/punisher_war_zone-230941957-large.jpg</fanart>
</item>
